{"results":[{"bounce_rate":100,"events":1,"exit_page":"/ja/dev/whatsnew/3.6.html","pageviews":1,"visit_duration":0,"visitors":1,"visits":1},{"bounce_rate":0,"events":6,"exit_page":"/ja/3.12/library/pathlib.html","pageviews":6,"visit_duration":626,"visitors":1,"visits":1},{"bounce_rate":100,"events":1,"exit_page":"/zh-tw/dev/library/markup.html","pageviews":1,"visit_duration":0,"visitors":1,"visits":1},{"bounce_rate":100,"events":1,"exit_page":"/zh-tw/3.13/whatsnew/3.10.html","pageviews":1,"visit_duration":0,"visitors":1,"visits":1},{"bounce_rate":0,"events":2,"exit_page":"/zh-tw/3.13/whatsnew/3.11.html","pageviews":2,"visit_duration":3,"visitors":1,"visits":1},{"bounce_rate":0,"events":2,"exit_page":"/ja/3.12/library/tempfile.html","pageviews":2,"visit_duration":52,"visitors":1,"visits":1},{"bounce_rate":100,"events":1,"exit_page":"/zh-cn/dev/library/grp.html","pageviews":1,"visit_duration":0,"visitors":1,"visits":1},{"bounce_rate":0,"events":3,"exit_page":"/tr/3.13/c-api/init_config.html","pageviews":3,"visit_duration":49,"visitors":1,"visits":1},{"bounce_rate":100,"events":1,"exit_page":"/zh-cn/3.12/c-api/veryhigh.html","pageviews":1,"visit_duration":0,"visitors":1,"visits":1},{"bounce_rate":0,"events":25,"exit_page":"/es/3.13/library/fractions.html","pageviews":25,"visit_duration":597,"visitors":1,"visits":1},{"bounce_rate":100,"events":1,"exit_page":"/zh-tw/3.13/faq/gui.html","pageviews":1,"visit_duration":0,"visitors":1,"visits":1},{"bounce_rate":0,"events":4,"exit_page":"/zh-cn/3.12/whatsnew/3.6.html","pageviews":4,"visit_duration":23,"visitors":1,"visits":1},{"bounce_rate":0,"events":7,"exit_page":"/3.12/library/unittest.mock-examples.html","pageviews":7,"visit_duration":187,"visitors":1,"visits":1},{"bounce_rate":100,"events":1,"exit_page":"/zh-cn/dev/library/asyncio-exceptions.html","pageviews":1,"visit_duration":0,"visitors":1,"visits":1},{"bounce_rate":0,"events":2,"exit_page":"/zh-cn/3.13/library/builtins.html","pageviews":2,"visit_duration":21,"visitors":1,"visits":1},{"bounce_rate":0,"events":5,"exit_page":"/3.11/c-api/none.html","pageviews":5,"visit_duration":21,"visitors":1,"visits":1},{"bounce_rate":100,"events":1,"exit_page":"/zh-cn/3.12/library/multiprocessing.shared_memory.html","pageviews":1,"visit_duration":0,"visitors":1,"visits":1},{"bounce_rate":100,"events":1,"exit_page":"/zh-tw/3.11/c-api/objbuffer.html","pageviews":1,"visit_duration":0,"visitors":1,"visits":1},{"bounce_rate":0,"events":4,"exit_page":"/3.13/library/xmlrpc.html","pageviews":4,"visit_duration":20,"visitors":1,"visits":1},{"bounce_rate":100,"events":2,"exit_page":"/3.12/library/warnings.html","pageviews":2,"visit_duration":0,"visitors":1,"visits":2},{"bounce_rate":100,"events":1,"exit_page":"/zh-tw/dev/library/index.html","pageviews":1,"visit_duration":0,"visitors":1,"visits":1},{"bounce_rate":0,"events":4,"exit_page":"/pt-br/dev/reference/lexical_analysis.html","pageviews":4,"visit_duration":130,"visitors":1,"visits":1},{"bounce_rate":100,"events":1,"exit_page":"/pl/3.11/library/asyncore.html","pageviews":1,"visit_duration":0,"visitors":1,"visits":1},{"bounce_rate":100,"events":1,"exit_page":"/zh-tw/3.11/distutils/setupscript.html","pageviews":1,"visit_duration":0,"visitors":1,"visits":1},{"bounce_rate":0,"events":2,"exit_page":"/zh-cn/3.11/genindex-拼.html","pageviews":2,"visit_duration":79,"visitors":1,"visits":1},{"bounce_rate":100,"events":1,"exit_page":"/zh-cn/3.13/library/codeop.html","pageviews":1,"visit_duration":0,"visitors":1,"visits":1},{"bounce_rate":100,"events":1,"exit_page":"/es/3/c-api/complex.html","pageviews":1,"visit_duration":0,"visitors":1,"visits":1},{"bounce_rate":0,"events":2,"exit_page":"/zh-cn/3.12/library/codecs.html","pageviews":2,"visit_duration":11,"visitors":1,"visits":1},{"bounce_rate":100,"events":1,"exit_page":"/es/dev/reference/simple_stmts.html","pageviews":1,"visit_duration":0,"visitors":1,"visits":1},{"bounce_rate":100,"events":2,"exit_page":"/3.11/library/xml.dom.pulldom.html","pageviews":2,"visit_duration":0,"visitors":1,"visits":2},{"bounce_rate":100,"events":1,"exit_page":"/zh-cn/3.12/library/importlib.metadata.html","pageviews":1,"visit_duration":0,"visitors":1,"visits":1},{"bounce_rate":100,"events":1,"exit_page":"/zh-tw/3.11/library/http.server.html","pageviews":1,"visit_duration":0,"visitors":1,"visits":1},{"bounce_rate":0,"events":4,"exit_page":"/fr/3.11/c-api/list.html","pageviews":4,"visit_duration":36,"visitors":1,"visits":1},{"bounce_rate":0,"events":5,"exit_page":"/tr/3/library/intro.html","pageviews":5,"visit_duration":49,"visitors":1,"visits":1},{"bounce_rate":100,"events":1,"exit_page":"/zh-tw/3.11/library/email.generator.html","pageviews":1,"visit_duration":0,"visitors":1,"visits":1},{"bounce_rate":100,"events":1,"exit_page":"/es/dev/whatsnew/2.0.html","pageviews":1,"visit_duration":0,"visitors":1,"visits":1},{"bounce_rate":0,"events":2,"exit_page":"/3.13/whatsnew/2.2.html","pageviews":2,"visit_duration":31,"visitors":1,"visits":1},{"bounce_rate":100,"events":1,"exit_page":"/ja/3.13/reference/import.html","pageviews":1,"visit_duration":0,"visitors":1,"visits":1},{"bounce_rate":0,"events":3,"exit_page":"/3.11/library/asyncio-api-index.html","pageviews":3,"visit_duration":1234,"visitors":1,"visits":1},{"bounce_rate":100,"events":1,"exit_page":"/zh-tw/3.12/library/idle.html","pageviews":1,"visit_duration":0,"visitors":1,"visits":1},{"bounce_rate":0,"events":3,"exit_page":"/fr/3/c-api/conversion.html","pageviews":3,"visit_duration":40,"visitors":1,"visits":1},{"bounce_rate":100,"events":1,"exit_page":"/pt-br/3.13/faq/programming.html","pageviews":1,"visit_duration":0,"visitors":1,"visits":1},{"bounce_rate":100,"events":1,"exit_page":"/fr/3/library/copyreg.html","pageviews":1,"visit_duration":0,"visitors":1,"visits":1},{"bounce_rate":0,"events":2,"exit_page":"/pt-br/dev/library/multiprocessing.html","pageviews":2,"visit_duration":814,"visitors":1,"visits":1},{"bounce_rate":0,"events":3,"exit_page":"/tr/3/library/platform.html","pageviews":3,"visit_duration":32,"visitors":1,"visits":1},{"bounce_rate":0,"events":14,"exit_page":"/dev/faq/index.html","pageviews":14,"visit_duration":583,"visitors":1,"visits":1},{"bounce_rate":0,"events":2,"exit_page":"/ko/3.11/library/select.html","pageviews":2,"visit_duration":8,"visitors":1,"visits":1},{"bounce_rate":0,"events":2,"exit_page":"/3.12/using/mac.html","pageviews":2,"visit_duration":96,"visitors":1,"visits":1},{"bounce_rate":100,"events":1,"exit_page":"/uk/3.12/library/curses.html","pageviews":1,"visit_duration":0,"visitors":1,"visits":1},{"bounce_rate":100,"events":1,"exit_page":"/uk/3/library/asyncore.html","pageviews":1,"visit_duration":0,"visitors":1,"visits":1},{"bounce_rate":0,"events":0,"exit_page":"/es/3.11/genindex-C.html","pageviews":0,"visit_duration":0,"visitors":1,"visits":0},{"bounce_rate":0,"events":12,"exit_page":"/es/3.11/library/fileinput.html","pageviews":12,"visit_duration":414,"visitors":1,"visits":1},{"bounce_rate":0,"events":14,"exit_page":"/zh-cn/3.12/library/tarfile.html","pageviews":14,"visit_duration":1554,"visitors":1,"visits":1},{"bounce_rate":0,"events":2,"exit_page":"/zh-tw/3.11/using/editors.html","pageviews":2,"visit_duration":1316,"visitors":1,"visits":1},{"bounce_rate":0,"events":2,"exit_page":"/uk/3/library/resource.html","pageviews":2,"visit_duration":72,"visitors":1,"visits":1},{"bounce_rate":0,"events":0,"exit_page":"/dev/genindex-D.html","pageviews":0,"visit_duration":0,"visitors":1,"visits":0}]}